tutormfe_extensions/__about__.py
tutormfe_extensions/__init__.py
tutormfe_extensions/patches/.gitignore
tutormfe_extensions/patches/caddyfile-cms
tutormfe_extensions/patches/caddyfile-lms
tutormfe_extensions/patches/caddyfile-mfe-by-path
tutormfe_extensions/patches/k8s-override
tutormfe_extensions/patches/mfe-dockerfile-pre-npm-build
tutormfe_extensions/patches/mfe-dockerfile-production-final
tutormfe_extensions/patches/openedx-cms-production-settings
tutormfe_extensions/patches/openedx-lms-production-settings
tutormfe_extensions/plugin.py
tutormfe_extensions/templates/mfe/build/mfe/docker-entrypoint.sh
tutormfe_extensions/templates/mfe_extensions/apps/.gitignore
tutormfe_extensions/templates/mfe_extensions/build/.gitignore
tutormfe_extensions/templates/mfe_extensions/jobs/init/.gitignore
tutormfe_extensions/templates/mfe_extensions/k8s/mfe-deployment-overrides.yml
tutor_contrib_mfe_extensions-21.0.0.dist-info/licenses/LICENSE
tutor_contrib_mfe_extensions-21.0.0.dist-info/WHEEL
tutor_contrib_mfe_extensions-21.0.0.dist-info/entry_points.txt
tutor_contrib_mfe_extensions-21.0.0.dist-info/METADATA
tutor_contrib_mfe_extensions-21.0.0.dist-info/RECORD
