Metadata-Version: 2.4
Name: tutor-contrib-mfe-extensions
Version: 21.0.0
Summary: mfe_extensions plugin for Tutor
Author: Moisés González
License-File: LICENSE
Classifier: Development Status :: 5 - Production/Stable
Classifier: Intended Audience :: Developers
Classifier: License :: OSI Approved :: GNU Affero General Public License v3
Classifier: Operating System :: OS Independent
Classifier: Programming Language :: Python
Classifier: Programming Language :: Python :: 3.10
Classifier: Programming Language :: Python :: 3.11
Classifier: Programming Language :: Python :: 3.12
Requires-Dist: tutor~=21.0
Requires-Dist: tutor-mfe~=21.0
Requires-Python: >=3.10
Project-URL: Code, https://github.com/edunext/tutor-contrib-mfe-extensions
Project-URL: Homepage, https://github.com/edunext/tutor-contrib-mfe-extensions
Project-URL: Issue tracker, https://github.com/edunext/tutor-contrib-mfe-extensions/issues
